src/__init__.py
src/config.py
src/main.py
src/agents/__init__.py
src/agents/analyzer.py
src/agents/documenter.py
src/agents/prompts/analyzer.yaml
src/agents/prompts/documenter.yaml
src/agents/tools/__init__.py
src/agents/tools/dir_tool/__init__.py
src/agents/tools/dir_tool/list_files.py
src/agents/tools/file_tool/__init__.py
src/agents/tools/file_tool/file_reader.py
src/handlers/__init__.py
src/handlers/analyze.py
src/handlers/base_handler.py
src/handlers/cronjob.py
src/handlers/readme.py
src/utils/__init__.py
src/utils/dict.py
src/utils/logger.py
src/utils/prompt_manager.py
src/utils/repo.py
src/utils/retry_client.py
src/utils/custom_models/__init__.py
src/utils/custom_models/gemini_provider.py
ai_doc_gen-1.0.0.dist-info/METADATA
ai_doc_gen-1.0.0.dist-info/WHEEL
ai_doc_gen-1.0.0.dist-info/entry_points.txt
ai_doc_gen-1.0.0.dist-info/licenses/LICENSE
ai_doc_gen-1.0.0.dist-info/RECORD
