Metadata-Version: 2.4
Name: ai-doc-gen
Version: 1.0.0
Summary: AI-powered code documentation generator that analyzes repositories and creates comprehensive documentation
Author-email: Milad Noroozi <norooziosos@gmail.com>
License-File: LICENSE
Requires-Python: <3.14,>=3.13
Requires-Dist: gitpython>=3.1.45
Requires-Dist: hatchling>=1.27.0
Requires-Dist: ipython>=9.4.0
Requires-Dist: jinja2>=3.1.6
Requires-Dist: langfuse>=3.2.2
Requires-Dist: logfire>=4.2.0
Requires-Dist: nest-asyncio>=1.6.0
Requires-Dist: opentelemetry-instrumentation-httpx>=0.57b0
Requires-Dist: psutil>=7.0.0
Requires-Dist: py-tools>=0.1.0
Requires-Dist: pydantic-ai[logfire]>=0.6.1
Requires-Dist: pydantic>=2.11.7
Requires-Dist: python-dotenv>=1.1.1
Requires-Dist: python-gitlab>=6.2.0
Requires-Dist: pyyaml>=6.0.2
Requires-Dist: ujson>=5.10.0
Provides-Extra: dev
Requires-Dist: ipython>=9.4.0; extra == 'dev'
